<?xml version="1.0" encoding="UTF-8" standalone="no"?>
<Configuration>
  <Components>
    <UniqueComponent dnOrder="0" id="cmsis"/>
    <UniqueComponent dnOrder="1" id="core">
      <Symbols dnOrder="0">
        <KeyValueSet dnOrder="0" id="COMPILER_CHOICE">
          <Values dnOrder="0">
            <Dynamic dnOrder="0" id="core" value="0"/>
          </Values>
        </KeyValueSet>
        <Boolean dnOrder="1" id="CONFIG_CLOCK_DFLL_ENABLE">
          <Values dnOrder="0">
            <Dynamic dnOrder="0" id="core" value="true"/>
          </Values>
        </Boolean>
        <Boolean dnOrder="2" id="CONFIG_CLOCK_OSC8M_ENABLE">
          <Values dnOrder="0">
            <Dynamic dnOrder="0" id="core" value="false"/>
          </Values>
        </Boolean>
        <Integer dnOrder="3" id="CPU_CLOCK_FREQUENCY">
          <Values dnOrder="0">
            <Dynamic dnOrder="0" id="core" value="48000000"/>
          </Values>
        </Integer>
        <KeyValueSet dnOrder="4" id="DEVICE_BOD33_ACTION">
          <Values dnOrder="0">
            <Dynamic dnOrder="0" id="core" value="1"/>
          </Values>
        </KeyValueSet>
        <KeyValueSet dnOrder="5" id="DEVICE_BOD33_EN">
          <Values dnOrder="0">
            <Dynamic dnOrder="0" id="core" value="1"/>
          </Values>
        </KeyValueSet>
        <KeyValueSet dnOrder="6" id="DEVICE_BOD33_HYST">
          <Values dnOrder="0">
            <Dynamic dnOrder="0" id="core" value="0"/>
          </Values>
        </KeyValueSet>
        <KeyValueSet dnOrder="7" id="DEVICE_SECURITY">
          <Values dnOrder="0">
            <Dynamic dnOrder="0" id="core" value="0"/>
          </Values>
        </KeyValueSet>
        <KeyValueSet dnOrder="8" id="DEVICE_WDT_ALWAYSON">
          <Values dnOrder="0">
            <Dynamic dnOrder="0" id="core" value="0"/>
          </Values>
        </KeyValueSet>
        <KeyValueSet dnOrder="9" id="DEVICE_WDT_ENABLE">
          <Values dnOrder="0">
            <Dynamic dnOrder="0" id="core" value="0"/>
          </Values>
        </KeyValueSet>
        <KeyValueSet dnOrder="10" id="DEVICE_WDT_WEN">
          <Values dnOrder="0">
            <Dynamic dnOrder="0" id="core" value="0"/>
          </Values>
        </KeyValueSet>
        <KeyValueSet dnOrder="11" id="DEVICE_WDT_WINDOW_0">
          <Values dnOrder="0">
            <Dynamic dnOrder="0" id="core" value="1"/>
          </Values>
        </KeyValueSet>
        <Hex dnOrder="12" id="DEVICE_WDT_WINDOW_1">
          <Values dnOrder="0">
            <Dynamic dnOrder="0" id="core" value="4"/>
          </Values>
        </Hex>
        <Integer dnOrder="13" id="DFLL_CLOCK_FREQ">
          <Values dnOrder="0">
            <Dynamic dnOrder="0" id="core" value="48000000"/>
          </Values>
        </Integer>
        <Integer dnOrder="14" id="DPLL_CLOCK_FREQ">
          <Values dnOrder="0">
            <Dynamic dnOrder="0" id="core" value="0"/>
          </Values>
        </Integer>
        <Integer dnOrder="15" id="GCLK_0_FREQ">
          <Values dnOrder="0">
            <Dynamic dnOrder="0" id="core" value="48000000"/>
          </Values>
        </Integer>
        <KeyValueSet dnOrder="16" id="GCLK_0_SRC">
          <Values dnOrder="0">
            <Dynamic dnOrder="0" id="core" value="7"/>
          </Values>
        </KeyValueSet>
        <Integer dnOrder="17" id="GCLK_1_FREQ">
          <Values dnOrder="0">
            <Dynamic dnOrder="0" id="core" value="0"/>
          </Values>
        </Integer>
        <Integer dnOrder="18" id="GCLK_2_FREQ">
          <Values dnOrder="0">
            <Dynamic dnOrder="0" id="core" value="0"/>
          </Values>
        </Integer>
        <Integer dnOrder="19" id="GCLK_3_FREQ">
          <Values dnOrder="0">
            <Dynamic dnOrder="0" id="core" value="0"/>
          </Values>
        </Integer>
        <Integer dnOrder="20" id="GCLK_4_FREQ">
          <Values dnOrder="0">
            <Dynamic dnOrder="0" id="core" value="0"/>
          </Values>
        </Integer>
        <Integer dnOrder="21" id="GCLK_5_FREQ">
          <Values dnOrder="0">
            <Dynamic dnOrder="0" id="core" value="0"/>
          </Values>
        </Integer>
        <Integer dnOrder="22" id="GCLK_6_FREQ">
          <Values dnOrder="0">
            <Dynamic dnOrder="0" id="core" value="0"/>
          </Values>
        </Integer>
        <Integer dnOrder="23" id="GCLK_7_FREQ">
          <Values dnOrder="0">
            <Dynamic dnOrder="0" id="core" value="0"/>
          </Values>
        </Integer>
        <Integer dnOrder="24" id="GCLK_8_FREQ">
          <Values dnOrder="0">
            <Dynamic dnOrder="0" id="core" value="0"/>
          </Values>
        </Integer>
        <Boolean dnOrder="25" id="GCLK_CYCLE_FORMED">
          <Values dnOrder="0">
            <Dynamic dnOrder="0" id="core" value="false"/>
          </Values>
        </Boolean>
        <Integer dnOrder="26" id="GCLK_IO_0_FREQ">
          <Values dnOrder="0">
            <Dynamic dnOrder="0" id="core" value="0"/>
          </Values>
        </Integer>
        <Integer dnOrder="27" id="GCLK_IO_1_FREQ">
          <Values dnOrder="0">
            <Dynamic dnOrder="0" id="core" value="0"/>
          </Values>
        </Integer>
        <Integer dnOrder="28" id="GCLK_IO_2_FREQ">
          <Values dnOrder="0">
            <Dynamic dnOrder="0" id="core" value="0"/>
          </Values>
        </Integer>
        <Integer dnOrder="29" id="GCLK_IO_3_FREQ">
          <Values dnOrder="0">
            <Dynamic dnOrder="0" id="core" value="0"/>
          </Values>
        </Integer>
        <Integer dnOrder="30" id="GCLK_IO_4_FREQ">
          <Values dnOrder="0">
            <Dynamic dnOrder="0" id="core" value="0"/>
          </Values>
        </Integer>
        <Integer dnOrder="31" id="GCLK_IO_5_FREQ">
          <Values dnOrder="0">
            <Dynamic dnOrder="0" id="core" value="0"/>
          </Values>
        </Integer>
        <Integer dnOrder="32" id="OSC8M_CLOCK_FREQ">
          <Values dnOrder="0">
            <Dynamic dnOrder="0" id="core" value="0"/>
          </Values>
        </Integer>
        <String dnOrder="33" id="PIN_1_DIR">
          <Values dnOrder="0">
            <User dnOrder="0" value="Out"/>
          </Values>
        </String>
        <String dnOrder="34" id="PIN_1_FUNCTION_NAME">
          <Values dnOrder="0">
            <User dnOrder="0" value="LED"/>
          </Values>
        </String>
        <String dnOrder="35" id="PIN_1_FUNCTION_TYPE">
          <Values dnOrder="0">
            <User dnOrder="0" value="GPIO"/>
          </Values>
        </String>
        <String dnOrder="36" id="PIN_1_INEN">
          <Values dnOrder="0">
            <User dnOrder="0" value=""/>
          </Values>
        </String>
        <String dnOrder="37" id="PIN_1_LAT">
          <Values dnOrder="0">
            <User dnOrder="0" value="High"/>
          </Values>
        </String>
        <String dnOrder="38" id="PIN_1_MODE">
          <Values dnOrder="0">
            <User dnOrder="0" value=""/>
          </Values>
        </String>
        <String dnOrder="39" id="PIN_1_PERIPHERAL_FUNCTION">
          <Values dnOrder="0">
            <User dnOrder="0" value="GPIO"/>
          </Values>
        </String>
        <String dnOrder="40" id="PIN_48_DIR">
          <Values dnOrder="0">
            <User dnOrder="0" value=""/>
          </Values>
        </String>
        <String dnOrder="41" id="PIN_48_FUNCTION_NAME">
          <Values dnOrder="0">
            <User dnOrder="0" value="SWITCH"/>
          </Values>
        </String>
        <String dnOrder="42" id="PIN_48_FUNCTION_TYPE">
          <Values dnOrder="0">
            <User dnOrder="0" value="GPIO"/>
          </Values>
        </String>
        <String dnOrder="43" id="PIN_48_INEN">
          <Values dnOrder="0">
            <User dnOrder="0" value="True"/>
          </Values>
        </String>
        <String dnOrder="44" id="PIN_48_LAT">
          <Values dnOrder="0">
            <User dnOrder="0" value="High"/>
          </Values>
        </String>
        <String dnOrder="45" id="PIN_48_MODE">
          <Values dnOrder="0">
            <User dnOrder="0" value=""/>
          </Values>
        </String>
        <String dnOrder="46" id="PIN_48_PERIPHERAL_FUNCTION">
          <Values dnOrder="0">
            <User dnOrder="0" value="GPIO"/>
          </Values>
        </String>
        <String dnOrder="47" id="PIN_48_PULLEN">
          <Values dnOrder="0">
            <User dnOrder="0" value="True"/>
          </Values>
        </String>
        <String dnOrder="48" id="PIN_7_DIR">
          <Values dnOrder="0">
            <User dnOrder="0" value=""/>
          </Values>
        </String>
        <String dnOrder="49" id="PIN_7_INEN">
          <Values dnOrder="0">
            <User dnOrder="0" value=""/>
          </Values>
        </String>
        <String dnOrder="50" id="PIN_7_PULLEN">
          <Values dnOrder="0">
            <User dnOrder="0" value=""/>
          </Values>
        </String>
        <Boolean dnOrder="51" id="PORT_GROUP_0">
          <Values dnOrder="0">
            <Dynamic dnOrder="0" id="core" value="true"/>
          </Values>
        </Boolean>
        <String dnOrder="52" id="PORT_GROUP_0_DIR">
          <Values dnOrder="0">
            <Dynamic dnOrder="0" id="core" value="0x1"/>
          </Values>
        </String>
        <String dnOrder="53" id="PORT_GROUP_0_OUT">
          <Values dnOrder="0">
            <Dynamic dnOrder="0" id="core" value="0x1"/>
          </Values>
        </String>
        <String dnOrder="54" id="PORT_GROUP_0_PAD_0">
          <Values dnOrder="0">
            <Dynamic dnOrder="0" id="core" value="PA00"/>
          </Values>
        </String>
        <String dnOrder="55" id="PORT_GROUP_0_PINCFG0">
          <Values dnOrder="0">
            <Dynamic dnOrder="0" id="core" value="0x0"/>
          </Values>
        </String>
        <String dnOrder="56" id="PORT_GROUP_0_PMUX0">
          <Values dnOrder="0">
            <Dynamic dnOrder="0" id="core" value="0x0"/>
          </Values>
        </String>
        <Boolean dnOrder="57" id="PORT_GROUP_1">
          <Values dnOrder="0">
            <Dynamic dnOrder="0" id="core" value="true"/>
          </Values>
        </Boolean>
        <String dnOrder="58" id="PORT_GROUP_1_DIR">
          <Values dnOrder="0">
            <Dynamic dnOrder="0" id="core" value="0x0"/>
          </Values>
        </String>
        <String dnOrder="59" id="PORT_GROUP_1_OUT">
          <Values dnOrder="0">
            <Dynamic dnOrder="0" id="core" value="0x8"/>
          </Values>
        </String>
        <String dnOrder="60" id="PORT_GROUP_1_PAD_3">
          <Values dnOrder="0">
            <Dynamic dnOrder="0" id="core" value="PB03"/>
          </Values>
        </String>
        <String dnOrder="61" id="PORT_GROUP_1_PINCFG3">
          <Values dnOrder="0">
            <Dynamic dnOrder="0" id="core" value="0x6"/>
          </Values>
        </String>
        <String dnOrder="62" id="PORT_GROUP_1_PINCFG6">
          <Values dnOrder="0">
            <Dynamic dnOrder="0" id="core" value="0x0"/>
          </Values>
        </String>
        <String dnOrder="63" id="PORT_GROUP_1_PMUX1">
          <Values dnOrder="0">
            <Dynamic dnOrder="0" id="core" value="0x0"/>
          </Values>
        </String>
      </Symbols>
    </UniqueComponent>
    <UniqueComponent dnOrder="2" id="dfp"/>
    <UniqueComponent dnOrder="3" id="evsys">
      <Symbols dnOrder="0">
        <Boolean dnOrder="0" id="EVSYS_CHANNEL_0_USER_READY">
          <Values dnOrder="0">
            <Dynamic dnOrder="0" id="evsys" value="false"/>
          </Values>
        </Boolean>
        <Boolean dnOrder="1" id="EVSYS_CHANNEL_10_USER_READY">
          <Values dnOrder="0">
            <Dynamic dnOrder="0" id="evsys" value="false"/>
          </Values>
        </Boolean>
        <Boolean dnOrder="2" id="EVSYS_CHANNEL_11_USER_READY">
          <Values dnOrder="0">
            <Dynamic dnOrder="0" id="evsys" value="false"/>
          </Values>
        </Boolean>
        <Boolean dnOrder="3" id="EVSYS_CHANNEL_1_USER_READY">
          <Values dnOrder="0">
            <Dynamic dnOrder="0" id="evsys" value="false"/>
          </Values>
        </Boolean>
        <Boolean dnOrder="4" id="EVSYS_CHANNEL_2_USER_READY">
          <Values dnOrder="0">
            <Dynamic dnOrder="0" id="evsys" value="false"/>
          </Values>
        </Boolean>
        <Boolean dnOrder="5" id="EVSYS_CHANNEL_3_USER_READY">
          <Values dnOrder="0">
            <Dynamic dnOrder="0" id="evsys" value="false"/>
          </Values>
        </Boolean>
        <Boolean dnOrder="6" id="EVSYS_CHANNEL_4_USER_READY">
          <Values dnOrder="0">
            <Dynamic dnOrder="0" id="evsys" value="false"/>
          </Values>
        </Boolean>
        <Boolean dnOrder="7" id="EVSYS_CHANNEL_5_USER_READY">
          <Values dnOrder="0">
            <Dynamic dnOrder="0" id="evsys" value="false"/>
          </Values>
        </Boolean>
        <Boolean dnOrder="8" id="EVSYS_CHANNEL_6_USER_READY">
          <Values dnOrder="0">
            <Dynamic dnOrder="0" id="evsys" value="false"/>
          </Values>
        </Boolean>
        <Boolean dnOrder="9" id="EVSYS_CHANNEL_7_USER_READY">
          <Values dnOrder="0">
            <Dynamic dnOrder="0" id="evsys" value="false"/>
          </Values>
        </Boolean>
        <Boolean dnOrder="10" id="EVSYS_CHANNEL_8_USER_READY">
          <Values dnOrder="0">
            <Dynamic dnOrder="0" id="evsys" value="false"/>
          </Values>
        </Boolean>
        <Boolean dnOrder="11" id="EVSYS_CHANNEL_9_USER_READY">
          <Values dnOrder="0">
            <Dynamic dnOrder="0" id="evsys" value="false"/>
          </Values>
        </Boolean>
      </Symbols>
    </UniqueComponent>
    <UniqueComponent dnOrder="4" id="nvmctrl">
      <Symbols dnOrder="0">
        <Integer dnOrder="0" id="NVM_RWS">
          <Values dnOrder="0">
            <Dynamic dnOrder="0" id="nvmctrl" value="1"/>
          </Values>
        </Integer>
      </Symbols>
    </UniqueComponent>
  </Components>
  <UserData>
    <GraphSettings canvasHeight="400" canvasWidth="400" dnOrder="0"/>
    <ComponentGraph dnOrder="1" id="__ROOTVIEW">
      <ElementPositions dnOrder="0">
        <ElementPosition dnOrder="0" id="cmsis" x="330" y="60"/>
        <ElementPosition dnOrder="1" id="core" x="560" y="20"/>
        <ElementPosition dnOrder="2" id="dfp" x="340" y="20"/>
        <ElementPosition dnOrder="3" id="evsys" x="180" y="20"/>
        <ElementPosition dnOrder="4" id="nvmctrl" x="20" y="20"/>
      </ElementPositions>
    </ComponentGraph>
  </UserData>
</Configuration>
