<?xml version="1.0" encoding="UTF-8" standalone="no"?>
<Configuration>
  <Components>
    <UniqueComponent dnOrder="0" id="cmsis"/>
    <UniqueComponent dnOrder="1" id="core">
      <Symbols dnOrder="0">
        <KeyValueSet dnOrder="0" id="COMPILER_CHOICE">
          <Values dnOrder="0">
            <Dynamic dnOrder="0" id="core" value="0"/>
          </Values>
        </KeyValueSet>
        <Boolean dnOrder="1" id="CONFIG_CLOCK_DPLL_ENABLE">
          <Values dnOrder="0">
            <Dynamic dnOrder="0" id="core" value="true"/>
          </Values>
        </Boolean>
        <Integer dnOrder="2" id="CONFIG_CLOCK_DPLL_LDR_INTEGER">
          <Values dnOrder="0">
            <Dynamic dnOrder="0" id="core" value="63"/>
          </Values>
        </Integer>
        <Float dnOrder="3" id="CONFIG_CLOCK_DPLL_MULTIPLIER_VALUE">
          <Values dnOrder="0">
            <Dynamic dnOrder="0" id="core" value="64.0"/>
          </Values>
        </Float>
        <KeyValueSet dnOrder="4" id="CONFIG_CLOCK_DPLL_REF_CLOCK">
          <Values dnOrder="0">
            <Dynamic dnOrder="0" id="core" value="2"/>
          </Values>
        </KeyValueSet>
        <Integer dnOrder="5" id="CPU_CLOCK_FREQUENCY">
          <Values dnOrder="0">
            <Dynamic dnOrder="0" id="core" value="32000000"/>
          </Values>
        </Integer>
        <Menu dnOrder="6" id="CoreIARMenu">
          <Attributes dnOrder="0">
            <Boolean dnOrder="0" id="visible">
              <Value dnOrder="0">false</Value>
            </Boolean>
          </Attributes>
        </Menu>
        <Menu dnOrder="7" id="CoreKEILMenu">
          <Attributes dnOrder="0">
            <Boolean dnOrder="0" id="visible">
              <Value dnOrder="0">false</Value>
            </Boolean>
          </Attributes>
        </Menu>
        <String dnOrder="8" id="CoreMainFileName">
          <Values dnOrder="0">
            <User dnOrder="0" value="main_l1x"/>
          </Values>
        </String>
        <KeyValueSet dnOrder="9" id="DEVICE_SECURITY">
          <Values dnOrder="0">
            <Dynamic dnOrder="0" id="core" value="0"/>
          </Values>
        </KeyValueSet>
        <Integer dnOrder="10" id="DPLL96M_CLOCK_FREQ">
          <Values dnOrder="0">
            <Dynamic dnOrder="0" id="core" value="64000000"/>
          </Values>
        </Integer>
        <Integer dnOrder="11" id="GCLK_0_DIV">
          <Values dnOrder="0">
            <Dynamic dnOrder="0" id="core" value="2"/>
          </Values>
        </Integer>
        <Integer dnOrder="12" id="GCLK_0_DIVIDER_VALUE">
          <Values dnOrder="0">
            <Dynamic dnOrder="0" id="core" value="2"/>
          </Values>
        </Integer>
        <Integer dnOrder="13" id="GCLK_0_FREQ">
          <Values dnOrder="0">
            <Dynamic dnOrder="0" id="core" value="32000000"/>
          </Values>
        </Integer>
        <KeyValueSet dnOrder="14" id="GCLK_0_SRC">
          <Values dnOrder="0">
            <Dynamic dnOrder="0" id="core" value="3"/>
          </Values>
        </KeyValueSet>
        <Integer dnOrder="15" id="GCLK_1_DIV">
          <Values dnOrder="0">
            <Dynamic dnOrder="0" id="core" value="4"/>
          </Values>
        </Integer>
        <Integer dnOrder="16" id="GCLK_1_DIVIDER_VALUE">
          <Values dnOrder="0">
            <Dynamic dnOrder="0" id="core" value="4"/>
          </Values>
        </Integer>
        <Integer dnOrder="17" id="GCLK_1_FREQ">
          <Values dnOrder="0">
            <Dynamic dnOrder="0" id="core" value="1000000"/>
          </Values>
        </Integer>
        <KeyValueSet dnOrder="18" id="GCLK_1_SRC">
          <Values dnOrder="0">
            <Dynamic dnOrder="0" id="core" value="1"/>
          </Values>
        </KeyValueSet>
        <Integer dnOrder="19" id="GCLK_2_FREQ">
          <Values dnOrder="0">
            <Dynamic dnOrder="0" id="core" value="0"/>
          </Values>
        </Integer>
        <Integer dnOrder="20" id="GCLK_3_FREQ">
          <Values dnOrder="0">
            <Dynamic dnOrder="0" id="core" value="0"/>
          </Values>
        </Integer>
        <Integer dnOrder="21" id="GCLK_4_FREQ">
          <Values dnOrder="0">
            <Dynamic dnOrder="0" id="core" value="0"/>
          </Values>
        </Integer>
        <ListEntry dnOrder="22" id="GCLK_CODE">
          <Attributes dnOrder="0">
            <StringArray dnOrder="0" id="values">
              <Values dnOrder="0">
                <Value dnOrder="0">&amp;#160;&amp;#160;&amp;#160;&amp;#160;GCLK1_Initialize();</Value>
                <Value dnOrder="1">&amp;#160;&amp;#160;&amp;#160;&amp;#160;FDPLL_Initialize();</Value>
                <Value dnOrder="2">&amp;#160;&amp;#160;&amp;#160;&amp;#160;GCLK0_Initialize();</Value>
              </Values>
            </StringArray>
          </Attributes>
        </ListEntry>
        <Boolean dnOrder="23" id="GCLK_CYCLE_FORMED">
          <Values dnOrder="0">
            <Dynamic dnOrder="0" id="core" value="false"/>
          </Values>
        </Boolean>
        <Boolean dnOrder="24" id="GCLK_ID_0_CHEN">
          <Values dnOrder="0">
            <Dynamic dnOrder="0" id="core" value="true"/>
          </Values>
        </Boolean>
        <Integer dnOrder="25" id="GCLK_ID_0_FREQ">
          <Values dnOrder="0">
            <Dynamic dnOrder="0" id="core" value="1000000"/>
          </Values>
        </Integer>
        <KeyValueSet dnOrder="26" id="GCLK_ID_0_GENSEL">
          <Values dnOrder="0">
            <Dynamic dnOrder="0" id="core" value="1"/>
          </Values>
        </KeyValueSet>
        <Boolean dnOrder="27" id="GCLK_ID_11_CHEN">
          <Values dnOrder="0">
            <Dynamic dnOrder="0" id="core" value="true"/>
          </Values>
        </Boolean>
        <Integer dnOrder="28" id="GCLK_ID_11_FREQ">
          <Values dnOrder="0">
            <Dynamic dnOrder="0" id="core" value="32000000"/>
          </Values>
        </Integer>
        <Boolean dnOrder="29" id="GCLK_INST_NUM1">
          <Values dnOrder="0">
            <Dynamic dnOrder="0" id="core" value="true"/>
          </Values>
        </Boolean>
        <String dnOrder="30" id="KEIL_STACK_HEAP_SIZE">
          <Values dnOrder="0">
            <Dynamic dnOrder="0" id="core" value="0x1200"/>
          </Values>
        </String>
        <File dnOrder="31" id="MAIN_C">
          <Attributes dnOrder="0">
            <String dnOrder="0" id="name">
              <Value dnOrder="0">main_l1x.c</Value>
            </String>
          </Attributes>
        </File>
        <String dnOrder="32" id="MCLK_APBC_INITIAL_VALUE">
          <Values dnOrder="0">
            <Dynamic dnOrder="0" id="core" value="0x1fff"/>
          </Values>
        </String>
        <Boolean dnOrder="33" id="NVIC_22_0_ENABLE">
          <Values dnOrder="0">
            <Dynamic dnOrder="0" id="core" value="true"/>
          </Values>
        </Boolean>
        <String dnOrder="34" id="NVIC_22_0_HANDLER">
          <Values dnOrder="0">
            <Dynamic dnOrder="0" id="core" value="SERCOM0_USART_InterruptHandler"/>
          </Values>
        </String>
        <Boolean dnOrder="35" id="NVIC_22_0_HANDLER_LOCK">
          <Values dnOrder="0">
            <Dynamic dnOrder="0" id="core" value="true"/>
          </Values>
        </Boolean>
        <Boolean dnOrder="36" id="NVIC_23_0_ENABLE">
          <Values dnOrder="0">
            <Dynamic dnOrder="0" id="core" value="true"/>
          </Values>
        </Boolean>
        <String dnOrder="37" id="NVIC_23_0_HANDLER">
          <Values dnOrder="0">
            <Dynamic dnOrder="0" id="core" value="SERCOM0_USART_InterruptHandler"/>
          </Values>
        </String>
        <Boolean dnOrder="38" id="NVIC_23_0_HANDLER_LOCK">
          <Values dnOrder="0">
            <Dynamic dnOrder="0" id="core" value="true"/>
          </Values>
        </Boolean>
        <Boolean dnOrder="39" id="NVIC_24_0_ENABLE">
          <Values dnOrder="0">
            <Dynamic dnOrder="0" id="core" value="true"/>
          </Values>
        </Boolean>
        <String dnOrder="40" id="NVIC_24_0_HANDLER">
          <Values dnOrder="0">
            <Dynamic dnOrder="0" id="core" value="SERCOM0_USART_InterruptHandler"/>
          </Values>
        </String>
        <Boolean dnOrder="41" id="NVIC_24_0_HANDLER_LOCK">
          <Values dnOrder="0">
            <Dynamic dnOrder="0" id="core" value="true"/>
          </Values>
        </Boolean>
        <Boolean dnOrder="42" id="NVIC_25_0_ENABLE">
          <Values dnOrder="0">
            <Dynamic dnOrder="0" id="core" value="true"/>
          </Values>
        </Boolean>
        <String dnOrder="43" id="NVIC_25_0_HANDLER">
          <Values dnOrder="0">
            <Dynamic dnOrder="0" id="core" value="SERCOM0_USART_InterruptHandler"/>
          </Values>
        </String>
        <Boolean dnOrder="44" id="NVIC_25_0_HANDLER_LOCK">
          <Values dnOrder="0">
            <Dynamic dnOrder="0" id="core" value="true"/>
          </Values>
        </Boolean>
        <String dnOrder="45" id="PIN_23_FUNCTION_TYPE">
          <Values dnOrder="0">
            <User dnOrder="0" value="SERCOM0_PAD2"/>
          </Values>
        </String>
        <String dnOrder="46" id="PIN_23_MODE">
          <Values dnOrder="0">
            <User dnOrder="0" value=""/>
          </Values>
        </String>
        <String dnOrder="47" id="PIN_23_PERIPHERAL_FUNCTION">
          <Values dnOrder="0">
            <User dnOrder="0" value="C"/>
          </Values>
        </String>
        <String dnOrder="48" id="PIN_24_FUNCTION_TYPE">
          <Values dnOrder="0">
            <User dnOrder="0" value="SERCOM0_PAD3"/>
          </Values>
        </String>
        <String dnOrder="49" id="PIN_24_MODE">
          <Values dnOrder="0">
            <User dnOrder="0" value=""/>
          </Values>
        </String>
        <String dnOrder="50" id="PIN_24_PERIPHERAL_FUNCTION">
          <Values dnOrder="0">
            <User dnOrder="0" value="C"/>
          </Values>
        </String>
        <String dnOrder="51" id="PIN_8_PERIPHERAL_FUNCTION">
          <Values dnOrder="0">
            <User dnOrder="0" value=""/>
          </Values>
        </String>
        <Boolean dnOrder="52" id="PORT_GROUP_0">
          <Values dnOrder="0">
            <Dynamic dnOrder="0" id="core" value="true"/>
          </Values>
        </Boolean>
        <String dnOrder="53" id="PORT_GROUP_0_DIR">
          <Values dnOrder="0">
            <Dynamic dnOrder="0" id="core" value="0x0"/>
          </Values>
        </String>
        <String dnOrder="54" id="PORT_GROUP_0_OUT">
          <Values dnOrder="0">
            <Dynamic dnOrder="0" id="core" value="0x0"/>
          </Values>
        </String>
        <String dnOrder="55" id="PORT_GROUP_0_PAD_25">
          <Values dnOrder="0">
            <Dynamic dnOrder="0" id="core" value="PA25"/>
          </Values>
        </String>
        <String dnOrder="56" id="PORT_GROUP_0_PAD_7">
          <Values dnOrder="0">
            <Dynamic dnOrder="0" id="core" value="PA07"/>
          </Values>
        </String>
        <String dnOrder="57" id="PORT_GROUP_0_PINCFG24">
          <Values dnOrder="0">
            <Dynamic dnOrder="0" id="core" value="0x1"/>
          </Values>
        </String>
        <String dnOrder="58" id="PORT_GROUP_0_PINCFG25">
          <Values dnOrder="0">
            <Dynamic dnOrder="0" id="core" value="0x1"/>
          </Values>
        </String>
        <String dnOrder="59" id="PORT_GROUP_0_PINCFG7">
          <Values dnOrder="0">
            <Dynamic dnOrder="0" id="core" value="0x0"/>
          </Values>
        </String>
        <String dnOrder="60" id="PORT_GROUP_0_PMUX12">
          <Values dnOrder="0">
            <Dynamic dnOrder="0" id="core" value="0x22"/>
          </Values>
        </String>
        <String dnOrder="61" id="PORT_GROUP_0_PMUX3">
          <Values dnOrder="0">
            <Dynamic dnOrder="0" id="core" value="0x2"/>
          </Values>
        </String>
        <String dnOrder="62" id="PORT_REG_NAME">
          <Values dnOrder="0">
            <Dynamic dnOrder="0" id="core" value="PORT"/>
          </Values>
        </String>
        <Boolean dnOrder="63" id="SERCOM0_0_INTERRUPT_ENABLE">
          <Values dnOrder="0">
            <Dynamic dnOrder="0" id="sercom0" value="true"/>
          </Values>
        </Boolean>
        <Boolean dnOrder="64" id="SERCOM0_0_INTERRUPT_ENABLE_UPDATE">
          <Values dnOrder="0">
            <Dynamic dnOrder="0" id="core" value="false"/>
          </Values>
        </Boolean>
        <String dnOrder="65" id="SERCOM0_0_INTERRUPT_HANDLER">
          <Values dnOrder="0">
            <Dynamic dnOrder="0" id="sercom0" value="SERCOM0_USART_InterruptHandler"/>
          </Values>
        </String>
        <Boolean dnOrder="66" id="SERCOM0_0_INTERRUPT_HANDLER_LOCK">
          <Values dnOrder="0">
            <Dynamic dnOrder="0" id="sercom0" value="true"/>
          </Values>
        </Boolean>
        <Boolean dnOrder="67" id="SERCOM0_1_INTERRUPT_ENABLE">
          <Values dnOrder="0">
            <Dynamic dnOrder="0" id="sercom0" value="true"/>
          </Values>
        </Boolean>
        <Boolean dnOrder="68" id="SERCOM0_1_INTERRUPT_ENABLE_UPDATE">
          <Values dnOrder="0">
            <Dynamic dnOrder="0" id="core" value="false"/>
          </Values>
        </Boolean>
        <String dnOrder="69" id="SERCOM0_1_INTERRUPT_HANDLER">
          <Values dnOrder="0">
            <Dynamic dnOrder="0" id="sercom0" value="SERCOM0_USART_InterruptHandler"/>
          </Values>
        </String>
        <Boolean dnOrder="70" id="SERCOM0_1_INTERRUPT_HANDLER_LOCK">
          <Values dnOrder="0">
            <Dynamic dnOrder="0" id="sercom0" value="true"/>
          </Values>
        </Boolean>
        <Boolean dnOrder="71" id="SERCOM0_2_INTERRUPT_ENABLE">
          <Values dnOrder="0">
            <Dynamic dnOrder="0" id="sercom0" value="true"/>
          </Values>
        </Boolean>
        <Boolean dnOrder="72" id="SERCOM0_2_INTERRUPT_ENABLE_UPDATE">
          <Values dnOrder="0">
            <Dynamic dnOrder="0" id="core" value="false"/>
          </Values>
        </Boolean>
        <String dnOrder="73" id="SERCOM0_2_INTERRUPT_HANDLER">
          <Values dnOrder="0">
            <Dynamic dnOrder="0" id="sercom0" value="SERCOM0_USART_InterruptHandler"/>
          </Values>
        </String>
        <Boolean dnOrder="74" id="SERCOM0_2_INTERRUPT_HANDLER_LOCK">
          <Values dnOrder="0">
            <Dynamic dnOrder="0" id="sercom0" value="true"/>
          </Values>
        </Boolean>
        <Boolean dnOrder="75" id="SERCOM0_CORE_CLOCK_ENABLE">
          <Values dnOrder="0">
            <Dynamic dnOrder="0" id="sercom0" value="true"/>
          </Values>
        </Boolean>
        <Integer dnOrder="76" id="SERCOM0_CORE_CLOCK_FREQUENCY">
          <Values dnOrder="0">
            <Dynamic dnOrder="0" id="core" value="32000000"/>
          </Values>
        </Integer>
        <Boolean dnOrder="77" id="SERCOM0_OTHER_INTERRUPT_ENABLE">
          <Values dnOrder="0">
            <Dynamic dnOrder="0" id="sercom0" value="true"/>
          </Values>
        </Boolean>
        <Boolean dnOrder="78" id="SERCOM0_OTHER_INTERRUPT_ENABLE_UPDATE">
          <Values dnOrder="0">
            <Dynamic dnOrder="0" id="core" value="false"/>
          </Values>
        </Boolean>
        <String dnOrder="79" id="SERCOM0_OTHER_INTERRUPT_HANDLER">
          <Values dnOrder="0">
            <Dynamic dnOrder="0" id="sercom0" value="SERCOM0_USART_InterruptHandler"/>
          </Values>
        </String>
        <Boolean dnOrder="80" id="SERCOM0_OTHER_INTERRUPT_HANDLER_LOCK">
          <Values dnOrder="0">
            <Dynamic dnOrder="0" id="sercom0" value="true"/>
          </Values>
        </Boolean>
        <String dnOrder="81" id="SYSTICK_PERIOD">
          <Values dnOrder="0">
            <Dynamic dnOrder="0" id="core" value="0x7d00"/>
          </Values>
        </String>
        <Integer dnOrder="82" id="SYSTICK_PERIOD_US">
          <Values dnOrder="0">
            <Dynamic dnOrder="0" id="core" value="1000"/>
          </Values>
        </Integer>
      </Symbols>
    </UniqueComponent>
    <UniqueComponent dnOrder="2" id="dfp"/>
    <UniqueComponent dnOrder="3" id="evsys">
      <Symbols dnOrder="0">
        <Boolean dnOrder="0" id="EVSYS_CHANNEL_0_USER_READY">
          <Values dnOrder="0">
            <Dynamic dnOrder="0" id="evsys" value="false"/>
          </Values>
        </Boolean>
        <Boolean dnOrder="1" id="EVSYS_CHANNEL_1_USER_READY">
          <Values dnOrder="0">
            <Dynamic dnOrder="0" id="evsys" value="false"/>
          </Values>
        </Boolean>
        <Boolean dnOrder="2" id="EVSYS_CHANNEL_2_USER_READY">
          <Values dnOrder="0">
            <Dynamic dnOrder="0" id="evsys" value="false"/>
          </Values>
        </Boolean>
        <Boolean dnOrder="3" id="EVSYS_CHANNEL_3_USER_READY">
          <Values dnOrder="0">
            <Dynamic dnOrder="0" id="evsys" value="false"/>
          </Values>
        </Boolean>
        <Boolean dnOrder="4" id="EVSYS_CHANNEL_4_USER_READY">
          <Values dnOrder="0">
            <Dynamic dnOrder="0" id="evsys" value="false"/>
          </Values>
        </Boolean>
        <Boolean dnOrder="5" id="EVSYS_CHANNEL_5_USER_READY">
          <Values dnOrder="0">
            <Dynamic dnOrder="0" id="evsys" value="false"/>
          </Values>
        </Boolean>
        <Boolean dnOrder="6" id="EVSYS_CHANNEL_6_USER_READY">
          <Values dnOrder="0">
            <Dynamic dnOrder="0" id="evsys" value="false"/>
          </Values>
        </Boolean>
        <Boolean dnOrder="7" id="EVSYS_CHANNEL_7_USER_READY">
          <Values dnOrder="0">
            <Dynamic dnOrder="0" id="evsys" value="false"/>
          </Values>
        </Boolean>
      </Symbols>
    </UniqueComponent>
    <UniqueComponent dnOrder="4" id="nvmctrl">
      <Symbols dnOrder="0">
        <Integer dnOrder="0" id="NVM_RWS">
          <Values dnOrder="0">
            <Dynamic dnOrder="0" id="nvmctrl" value="1"/>
          </Values>
        </Integer>
      </Symbols>
    </UniqueComponent>
    <UniqueComponent dnOrder="5" id="pm">
      <Symbols dnOrder="0">
        <KeyValueSet dnOrder="0" id="PM_PLCFG_PLSEL">
          <Values dnOrder="0">
            <Dynamic dnOrder="0" id="pm" value="1"/>
          </Values>
        </KeyValueSet>
      </Symbols>
    </UniqueComponent>
    <UniqueComponent dnOrder="6" id="sercom0">
      <Symbols dnOrder="0">
        <Hex dnOrder="0" id="I2CM_BAUD">
          <Values dnOrder="0">
            <Dynamic dnOrder="0" id="sercom0" value="153"/>
          </Values>
        </Hex>
        <File dnOrder="1" id="SERCOM_USART_HEADER">
          <Attributes dnOrder="0">
            <String dnOrder="0" id="source">
              <Value dnOrder="0">../peripheral/sercom_u2201/templates/plib_sercom_usart_ring_buffer.h.ftl</Value>
            </String>
          </Attributes>
        </File>
        <File dnOrder="2" id="SERCOM_USART_SOURCE">
          <Attributes dnOrder="0">
            <String dnOrder="0" id="source">
              <Value dnOrder="0">../peripheral/sercom_u2201/templates/plib_sercom_usart_ring_buffer.c.ftl</Value>
            </String>
          </Attributes>
        </File>
        <Integer dnOrder="3" id="SPI_BAUD_REG_VALUE">
          <Values dnOrder="0">
            <Dynamic dnOrder="0" id="sercom0" value="15"/>
          </Values>
        </Integer>
        <Integer dnOrder="4" id="USART_BAUD_VALUE">
          <Values dnOrder="0">
            <Dynamic dnOrder="0" id="sercom0" value="61761"/>
          </Values>
        </Integer>
        <Boolean dnOrder="5" id="USART_INTERRUPT_MODE">
          <Attributes dnOrder="0">
            <Boolean dnOrder="0" id="readOnly">
              <Value dnOrder="0">true</Value>
            </Boolean>
          </Attributes>
        </Boolean>
        <Boolean dnOrder="6" id="USART_RING_BUFFER_ENABLE">
          <Values dnOrder="0">
            <User dnOrder="0" value="true"/>
          </Values>
        </Boolean>
        <KeyValueSet dnOrder="7" id="USART_RXPO">
          <Values dnOrder="0">
            <User dnOrder="0" value="3"/>
          </Values>
        </KeyValueSet>
        <Integer dnOrder="8" id="USART_RX_RING_BUFFER_SIZE">
          <Attributes dnOrder="0">
            <Boolean dnOrder="0" id="visible">
              <Value dnOrder="0">true</Value>
            </Boolean>
          </Attributes>
          <Values dnOrder="1">
            <User dnOrder="0" value="20"/>
          </Values>
        </Integer>
        <Integer dnOrder="9" id="USART_SAMPLE_COUNT">
          <Values dnOrder="0">
            <Dynamic dnOrder="0" id="sercom0" value="16"/>
          </Values>
        </Integer>
        <Integer dnOrder="10" id="USART_SAMPLE_RATE">
          <Values dnOrder="0">
            <Dynamic dnOrder="0" id="sercom0" value="0"/>
          </Values>
        </Integer>
        <KeyValueSet dnOrder="11" id="USART_TXPO">
          <Values dnOrder="0">
            <User dnOrder="0" value="1"/>
          </Values>
        </KeyValueSet>
        <Integer dnOrder="12" id="USART_TX_RING_BUFFER_SIZE">
          <Attributes dnOrder="0">
            <Boolean dnOrder="0" id="visible">
              <Value dnOrder="0">true</Value>
            </Boolean>
          </Attributes>
        </Integer>
      </Symbols>
    </UniqueComponent>
  </Components>
  <UserData>
    <ComponentGraph dnOrder="0" id="__ROOTVIEW">
      <ElementPositions dnOrder="0">
        <ElementPosition dnOrder="0" id="cmsis" x="330" y="60"/>
        <ElementPosition dnOrder="1" id="core" x="720" y="20"/>
        <ElementPosition dnOrder="2" id="dfp" x="340" y="20"/>
        <ElementPosition dnOrder="3" id="evsys" x="180" y="20"/>
        <ElementPosition dnOrder="4" id="nvmctrl" x="20" y="20"/>
        <ElementPosition dnOrder="5" id="pm" x="560" y="20"/>
        <ElementPosition dnOrder="6" id="sercom0" x="170" y="80"/>
      </ElementPositions>
    </ComponentGraph>
    <GraphSettings canvasHeight="400" canvasWidth="400" dnOrder="1"/>
  </UserData>
</Configuration>
